rqbit_client/__init__.py
rqbit_client/__main__.py
rqbit_client/mcp_server.py
rqbit_client/wrapper/__init__.py
rqbit_client/wrapper/client.py
rqbit_client/wrapper/exceptions.py
rqbit_mcp-0.10.0.dist-info/METADATA
rqbit_mcp-0.10.0.dist-info/WHEEL
rqbit_mcp-0.10.0.dist-info/entry_points.txt
rqbit_mcp-0.10.0.dist-info/licenses/LICENSE
rqbit_mcp-0.10.0.dist-info/RECORD
