Metadata-Version: 2.4
Name: rqbit-mcp
Version: 0.10.0
Summary: Python wrapper & MCP server for the rqbit API
Project-URL: Repository, https://github.com/philogicae/rqbit-mcp
Project-URL: Release, https://github.com/philogicae/rqbit-mcp/releases
Project-URL: DeepWiki, https://deepwiki.com/philogicae/rqbit-mcp
Author: philogicae
License-File: LICENSE
Classifier: License :: OSI Approved :: MIT License
Classifier: Operating System :: OS Independent
Classifier: Programming Language :: Python :: 3
Requires-Python: <4.0,>=3.10
Requires-Dist: fastmcp
Requires-Dist: httpx[http2]
Requires-Dist: python-dotenv
